geocsvlib/__init__.py
geocsvlib/__main__.py
geocsvlib/constants/__init__.py
geocsvlib/dao/__init__.py
geocsvlib/dao/mongodb/__init__.py
geocsvlib/dao/mongodb/geolocation.py
geocsvlib/dao/mongodb/ip_geolocation.py
geocsvlib/dao/postgres/__init__.py
geocsvlib/dao/postgres/geolocation.py
geocsvlib/dao/sqlite/__init__.py
geocsvlib/dao/sqlite/geolocation.py
geocsvlib/dao/sqlite/ip_geolocation.py
geocsvlib/models/__init__.py
geocsvlib/models/connection_factory.py
geocsvlib/models/model_factory.py
geocsvlib/parsers/__init__.py
geocsvlib/parsers/loader.py
geocsvlib/parsers/reader.py
geocsvlib/utils/__init__.py
geocsvlib/utils/logger.py
geocsvlib-0.1.8.data/scripts/geocsv
geocsvlib-0.1.8.dist-info/DESCRIPTION.rst
geocsvlib-0.1.8.dist-info/METADATA
geocsvlib-0.1.8.dist-info/RECORD
geocsvlib-0.1.8.dist-info/WHEEL
geocsvlib-0.1.8.dist-info/metadata.json
geocsvlib-0.1.8.dist-info/top_level.txt
tests/__init__.py
tests/geocsvlib_test/__init__.py
tests/geocsvlib_test/constants_test.py
tests/geocsvlib_test/geocsv_test.py
tests/geocsvlib_test/dao_test/__init__.py
tests/geocsvlib_test/dao_test/mongodb/__init__.py
tests/geocsvlib_test/dao_test/mongodb/geolocation_test.py
tests/geocsvlib_test/models_test/__init__.py
tests/geocsvlib_test/models_test/connection_factory_test.py
tests/geocsvlib_test/parsers_test/__init__.py
tests/geocsvlib_test/parsers_test/loader_test.py
tests/geocsvlib_test/parsers_test/reader_test.py
