Metadata-Version: 2.0
Name: geocsvlib
Version: 0.1.8
Summary: IP Geolocation data CSV Parser Library
Home-page: http://github.com/rayattack/geocsvlib
Author: Raymond Ortserga
Author-email: ortserga@yahoo.com
License: MIT
Keywords: IP Location Parser CSV
Platform: UNKNOWN
Classifier: Development Status :: 3 - Alpha
Classifier: Programming Language :: Python :: 2.6
Classifier: Programming Language :: Python :: 2.7
Classifier: Programming Language :: Python :: Implementation :: CPython
Classifier: Topic :: Utilities
Classifier: Topic :: Software Development
Requires-Dist: mongoengine
